{
  "generated_at": "2025-11-04T19:32:01.805290+00:00",
  "count": 107,
  "wallpapers": [
    {
      "filename": "colorful-knit-pattern-preppy.jpg",
      "url": "wallpapers-mobile/colorful-knit-pattern-preppy.jpg",
      "thumb_url": "thumbnail/mobile-wallpapers-thumb/colorful-knit-pattern-preppy.webp",
      "size": 2915022,
      "modified": "2025-10-29T17:31:03.541619+00:00",
      "category": "uncategorized"
    },
    {
      "filename": "Dark-Netflix.png",
      "url": "wallpapers-mobile/Dark-Netflix.png",
      "thumb_url": "thumbnail/mobile-wallpapers-thumb/Dark-Netflix.webp",
      "size": 2371659,
      "modified": "2025-10-24T20:40:45.071066+00:00",
      "category": "uncategorized"
    },
    {
      "filename": "flowerpot-window.jpg",
      "url": "wallpapers-mobile/flowerpot-window.jpg",
      "thumb_url": "thumbnail/mobile-wallpapers-thumb/flowerpot-window.webp",
      "size": 476083,
      "modified": "2025-10-30T20:53:33.165190+00:00",
      "category": "uncategorized"
    },
    {
      "filename": "hexagon_colors.jpeg",
      "url": "wallpapers-mobile/hexagon_colors.jpeg",
      "thumb_url": "thumbnail/mobile-wallpapers-thumb/hexagon_colors.webp",
      "size": 208771,
      "modified": "2025-10-24T20:06:06.650185+00:00",
      "category": "uncategorized"
    },
    {
      "filename": "reach-for-it.png",
      "url": "wallpapers-mobile/reach-for-it.png",
      "thumb_url": "thumbnail/mobile-wallpapers-thumb/reach-for-it.webp",
      "size": 2087937,
      "modified": "2025-10-24T19:14:42.206516+00:00",
      "category": "uncategorized"
    },
    {
      "filename": "science.jpg",
      "url": "wallpapers-mobile/science.jpg",
      "thumb_url": "thumbnail/mobile-wallpapers-thumb/science.webp",
      "size": 1228822,
      "modified": "2025-10-26T17:44:41.785569+00:00",
      "category": "uncategorized"
    },
    {
      "filename": "skull.jpg",
      "url": "wallpapers-mobile/skull.jpg",
      "thumb_url": "thumbnail/mobile-wallpapers-thumb/skull.webp",
      "size": 1199636,
      "modified": "2025-10-24T18:25:06.595993+00:00",
      "category": "uncategorized"
    },
    {
      "filename": "tree-light.jpg",
      "url": "wallpapers-mobile/tree-light.jpg",
      "thumb_url": "thumbnail/mobile-wallpapers-thumb/tree-light.webp",
      "size": 3233541,
      "modified": "2025-10-24T10:13:49.397163+00:00",
      "category": "uncategorized"
    },
    {
      "filename": "abstract-1.png",
      "url": "wallpapers-mobile/abstract/abstract-1.png",
      "thumb_url": "thumbnail/mobile-wallpapers-thumb/abstract/abstract-1.webp",
      "size": 2200775,
      "modified": "2025-10-25T23:32:54.152755+00:00",
      "category": "abstract"
    },
    {
      "filename": "abstract-10.jpg",
      "url": "wallpapers-mobile/abstract/abstract-10.jpg",
      "thumb_url": "thumbnail/mobile-wallpapers-thumb/abstract/abstract-10.webp",
      "size": 804482,
      "modified": "2025-10-26T17:44:28.745281+00:00",
      "category": "abstract"
    },
    {
      "filename": "abstract-11.jpg",
      "url": "wallpapers-mobile/abstract/abstract-11.jpg",
      "thumb_url": "thumbnail/mobile-wallpapers-thumb/abstract/abstract-11.webp",
      "size": 1109392,
      "modified": "2025-10-26T20:28:45.975228+00:00",
      "category": "abstract"
    },
    {
      "filename": "abstract-2.jpg",
      "url": "wallpapers-mobile/abstract/abstract-2.jpg",
      "thumb_url": "thumbnail/mobile-wallpapers-thumb/abstract/abstract-2.webp",
      "size": 143773,
      "modified": "2025-10-25T23:16:43.019763+00:00",
      "category": "abstract"
    },
    {
      "filename": "abstract-3.jpg",
      "url": "wallpapers-mobile/abstract/abstract-3.jpg",
      "thumb_url": "thumbnail/mobile-wallpapers-thumb/abstract/abstract-3.webp",
      "size": 279396,
      "modified": "2025-10-26T15:29:23.794277+00:00",
      "category": "abstract"
    },
    {
      "filename": "abstract-4.jpg",
      "url": "wallpapers-mobile/abstract/abstract-4.jpg",
      "thumb_url": "thumbnail/mobile-wallpapers-thumb/abstract/abstract-4.webp",
      "size": 492568,
      "modified": "2025-10-26T15:29:57.767491+00:00",
      "category": "abstract"
    },
    {
      "filename": "abstract-5.jpg",
      "url": "wallpapers-mobile/abstract/abstract-5.jpg",
      "thumb_url": "thumbnail/mobile-wallpapers-thumb/abstract/abstract-5.webp",
      "size": 477223,
      "modified": "2025-10-26T17:48:14.422575+00:00",
      "category": "abstract"
    },
    {
      "filename": "abstract-6.jpg",
      "url": "wallpapers-mobile/abstract/abstract-6.jpg",
      "thumb_url": "thumbnail/mobile-wallpapers-thumb/abstract/abstract-6.webp",
      "size": 533951,
      "modified": "2025-10-26T17:45:16.254245+00:00",
      "category": "abstract"
    },
    {
      "filename": "abstract-7.jpg",
      "url": "wallpapers-mobile/abstract/abstract-7.jpg",
      "thumb_url": "thumbnail/mobile-wallpapers-thumb/abstract/abstract-7.webp",
      "size": 523528,
      "modified": "2025-10-26T17:45:28.998468+00:00",
      "category": "abstract"
    },
    {
      "filename": "abstract-8.jpg",
      "url": "wallpapers-mobile/abstract/abstract-8.jpg",
      "thumb_url": "thumbnail/mobile-wallpapers-thumb/abstract/abstract-8.webp",
      "size": 434623,
      "modified": "2025-10-26T17:45:18.383283+00:00",
      "category": "abstract"
    },
    {
      "filename": "abstract-9-dark.jpg",
      "url": "wallpapers-mobile/abstract/abstract-9-dark.jpg",
      "thumb_url": "thumbnail/mobile-wallpapers-thumb/abstract/abstract-9-dark.webp",
      "size": 836919,
      "modified": "2025-10-26T20:29:44.211021+00:00",
      "category": "abstract"
    },
    {
      "filename": "abstract-9.jpg",
      "url": "wallpapers-mobile/abstract/abstract-9.jpg",
      "thumb_url": "thumbnail/mobile-wallpapers-thumb/abstract/abstract-9.webp",
      "size": 734340,
      "modified": "2025-10-26T17:46:58.249743+00:00",
      "category": "abstract"
    },
    {
      "filename": "water-drops-microscope.jpg",
      "url": "wallpapers-mobile/abstract/water-drops-microscope.jpg",
      "thumb_url": "thumbnail/mobile-wallpapers-thumb/abstract/water-drops-microscope.webp",
      "size": 1626651,
      "modified": "2025-10-25T20:58:37.184969+00:00",
      "category": "abstract"
    },
    {
      "filename": "x-o.jpg",
      "url": "wallpapers-mobile/abstract/x-o.jpg",
      "thumb_url": "thumbnail/mobile-wallpapers-thumb/abstract/x-o.webp",
      "size": 1286273,
      "modified": "2025-10-26T20:28:33.893064+00:00",
      "category": "abstract"
    },
    {
      "filename": "aesthetic-guitar.jpg",
      "url": "wallpapers-mobile/aesthetic/aesthetic-guitar.jpg",
      "thumb_url": "thumbnail/mobile-wallpapers-thumb/aesthetic/aesthetic-guitar.webp",
      "size": 1437233,
      "modified": "2025-10-26T17:45:11.780163+00:00",
      "category": "aesthetic"
    },
    {
      "filename": "alley.jpg",
      "url": "wallpapers-mobile/aesthetic/alley.jpg",
      "thumb_url": "thumbnail/mobile-wallpapers-thumb/aesthetic/alley.webp",
      "size": 1947421,
      "modified": "2025-10-26T15:19:49.312596+00:00",
      "category": "aesthetic"
    },
    {
      "filename": "gentle-purple.jpg",
      "url": "wallpapers-mobile/aesthetic/gentle-purple.jpg",
      "thumb_url": "thumbnail/mobile-wallpapers-thumb/aesthetic/gentle-purple.webp",
      "size": 370436,
      "modified": "2025-10-30T20:54:32.817262+00:00",
      "category": "aesthetic"
    },
    {
      "filename": "spiderman-wall.png",
      "url": "wallpapers-mobile/aesthetic/spiderman-wall.png",
      "thumb_url": "thumbnail/mobile-wallpapers-thumb/aesthetic/spiderman-wall.webp",
      "size": 2880685,
      "modified": "2025-10-25T23:32:28.518944+00:00",
      "category": "aesthetic"
    },
    {
      "filename": "bcat_1.jpg",
      "url": "wallpapers-mobile/animals/bcat_1.jpg",
      "thumb_url": "thumbnail/mobile-wallpapers-thumb/animals/bcat_1.webp",
      "size": 15425,
      "modified": "2025-10-25T21:02:54.269346+00:00",
      "category": "animals"
    },
    {
      "filename": "bcat_2.jpg",
      "url": "wallpapers-mobile/animals/bcat_2.jpg",
      "thumb_url": "thumbnail/mobile-wallpapers-thumb/animals/bcat_2.webp",
      "size": 99054,
      "modified": "2025-10-25T21:03:05.314354+00:00",
      "category": "animals"
    },
    {
      "filename": "bcat_3.jpg",
      "url": "wallpapers-mobile/animals/bcat_3.jpg",
      "thumb_url": "thumbnail/mobile-wallpapers-thumb/animals/bcat_3.webp",
      "size": 259068,
      "modified": "2025-10-25T21:03:15.372922+00:00",
      "category": "animals"
    },
    {
      "filename": "cat_landscape.jpg",
      "url": "wallpapers-mobile/animals/cat_landscape.jpg",
      "thumb_url": "thumbnail/mobile-wallpapers-thumb/animals/cat_landscape.webp",
      "size": 290995,
      "modified": "2025-10-24T18:24:37.166913+00:00",
      "category": "animals"
    },
    {
      "filename": "cute.jpg",
      "url": "wallpapers-mobile/animals/cute.jpg",
      "thumb_url": "thumbnail/mobile-wallpapers-thumb/animals/cute.webp",
      "size": 445813,
      "modified": "2025-10-24T20:40:21.690816+00:00",
      "category": "animals"
    },
    {
      "filename": "snow_cat.jpg",
      "url": "wallpapers-mobile/animals/snow_cat.jpg",
      "thumb_url": "thumbnail/mobile-wallpapers-thumb/animals/snow_cat.webp",
      "size": 300252,
      "modified": "2025-10-24T18:24:07.089094+00:00",
      "category": "animals"
    },
    {
      "filename": "chainsaw-man-denji-purple.jpg",
      "url": "wallpapers-mobile/anime/chainsaw-man-denji-purple.jpg",
      "thumb_url": "thumbnail/mobile-wallpapers-thumb/anime/chainsaw-man-denji-purple.webp",
      "size": 795468,
      "modified": "2025-10-29T17:24:39.183622+00:00",
      "category": "anime"
    },
    {
      "filename": "cyberpunk-edgerunners-image.jpg",
      "url": "wallpapers-mobile/anime/cyberpunk-edgerunners-image.jpg",
      "thumb_url": "thumbnail/mobile-wallpapers-thumb/anime/cyberpunk-edgerunners-image.webp",
      "size": 2662505,
      "modified": "2025-10-27T05:36:40.677881+00:00",
      "category": "anime"
    },
    {
      "filename": "cyberpunk-edgerunners.jpg",
      "url": "wallpapers-mobile/anime/cyberpunk-edgerunners.jpg",
      "thumb_url": "thumbnail/mobile-wallpapers-thumb/anime/cyberpunk-edgerunners.webp",
      "size": 835588,
      "modified": "2025-10-27T05:36:43.028950+00:00",
      "category": "anime"
    },
    {
      "filename": "konan.jpg",
      "url": "wallpapers-mobile/anime/konan.jpg",
      "thumb_url": "thumbnail/mobile-wallpapers-thumb/anime/konan.webp",
      "size": 1274316,
      "modified": "2025-10-29T17:15:37.160711+00:00",
      "category": "anime"
    },
    {
      "filename": "naruto-six-sage.jpg",
      "url": "wallpapers-mobile/anime/naruto-six-sage.jpg",
      "thumb_url": "thumbnail/mobile-wallpapers-thumb/anime/naruto-six-sage.webp",
      "size": 218151,
      "modified": "2025-10-26T15:28:33.966962+00:00",
      "category": "anime"
    },
    {
      "filename": "naruto.jpg",
      "url": "wallpapers-mobile/anime/naruto.jpg",
      "thumb_url": "thumbnail/mobile-wallpapers-thumb/anime/naruto.webp",
      "size": 402352,
      "modified": "2025-10-29T17:11:58.000951+00:00",
      "category": "anime"
    },
    {
      "filename": "Acclaimed_rectangle.jpg",
      "url": "wallpapers-mobile/art/Acclaimed_rectangle.jpg",
      "thumb_url": "thumbnail/mobile-wallpapers-thumb/art/Acclaimed_rectangle.webp",
      "size": 475560,
      "modified": "2025-10-24T18:25:22.124443+00:00",
      "category": "art"
    },
    {
      "filename": "asciiflowers.png",
      "url": "wallpapers-mobile/art/asciiflowers.png",
      "thumb_url": "thumbnail/mobile-wallpapers-thumb/art/asciiflowers.webp",
      "size": 2746224,
      "modified": "2025-10-24T18:25:52.303389+00:00",
      "category": "art"
    },
    {
      "filename": "cat-in-rain.jpg",
      "url": "wallpapers-mobile/art/cat-in-rain.jpg",
      "thumb_url": "thumbnail/mobile-wallpapers-thumb/art/cat-in-rain.webp",
      "size": 498977,
      "modified": "2025-10-26T15:29:29.289312+00:00",
      "category": "art"
    },
    {
      "filename": "evening.jpg",
      "url": "wallpapers-mobile/art/evening.jpg",
      "thumb_url": "thumbnail/mobile-wallpapers-thumb/art/evening.webp",
      "size": 279976,
      "modified": "2025-10-24T19:17:00.348897+00:00",
      "category": "art"
    },
    {
      "filename": "eye.jpg",
      "url": "wallpapers-mobile/art/eye.jpg",
      "thumb_url": "thumbnail/mobile-wallpapers-thumb/art/eye.webp",
      "size": 1211412,
      "modified": "2025-10-26T17:44:03.393659+00:00",
      "category": "art"
    },
    {
      "filename": "pixel-pond.jpg",
      "url": "wallpapers-mobile/art/pixel-pond.jpg",
      "thumb_url": "thumbnail/mobile-wallpapers-thumb/art/pixel-pond.webp",
      "size": 393605,
      "modified": "2025-10-25T23:31:56.753684+00:00",
      "category": "art"
    },
    {
      "filename": "Pixelated_forest.png",
      "url": "wallpapers-mobile/art/Pixelated_forest.png",
      "thumb_url": "thumbnail/mobile-wallpapers-thumb/art/Pixelated_forest.webp",
      "size": 468454,
      "modified": "2025-10-24T20:38:28.210634+00:00",
      "category": "art"
    },
    {
      "filename": "princess-mononoke.jpg",
      "url": "wallpapers-mobile/art/princess-mononoke.jpg",
      "thumb_url": "thumbnail/mobile-wallpapers-thumb/art/princess-mononoke.webp",
      "size": 2004034,
      "modified": "2025-10-29T17:29:56.245006+00:00",
      "category": "art"
    },
    {
      "filename": "red-samurai.jpg",
      "url": "wallpapers-mobile/art/red-samurai.jpg",
      "thumb_url": "thumbnail/mobile-wallpapers-thumb/art/red-samurai.webp",
      "size": 169327,
      "modified": "2025-10-25T23:30:57.953954+00:00",
      "category": "art"
    },
    {
      "filename": "road.jpg",
      "url": "wallpapers-mobile/art/road.jpg",
      "thumb_url": "thumbnail/mobile-wallpapers-thumb/art/road.webp",
      "size": 1672524,
      "modified": "2025-10-26T20:29:57.956208+00:00",
      "category": "art"
    },
    {
      "filename": "sakura.jpg",
      "url": "wallpapers-mobile/art/sakura.jpg",
      "thumb_url": "thumbnail/mobile-wallpapers-thumb/art/sakura.webp",
      "size": 1794343,
      "modified": "2025-10-26T20:29:11.828580+00:00",
      "category": "art"
    },
    {
      "filename": "skull-ascii.jpg",
      "url": "wallpapers-mobile/art/skull-ascii.jpg",
      "thumb_url": "thumbnail/mobile-wallpapers-thumb/art/skull-ascii.webp",
      "size": 437025,
      "modified": "2025-10-26T14:44:57.518796+00:00",
      "category": "art"
    },
    {
      "filename": "studio-ghibli-wallpaper.jpg",
      "url": "wallpapers-mobile/art/studio-ghibli-wallpaper.jpg",
      "thumb_url": "thumbnail/mobile-wallpapers-thumb/art/studio-ghibli-wallpaper.webp",
      "size": 1014780,
      "modified": "2025-10-26T15:19:17.924391+00:00",
      "category": "art"
    },
    {
      "filename": "sunset-house.jpg",
      "url": "wallpapers-mobile/art/sunset-house.jpg",
      "thumb_url": "thumbnail/mobile-wallpapers-thumb/art/sunset-house.webp",
      "size": 2747636,
      "modified": "2025-10-26T15:19:03.386295+00:00",
      "category": "art"
    },
    {
      "filename": "tree-boy.jpg",
      "url": "wallpapers-mobile/art/tree-boy.jpg",
      "thumb_url": "thumbnail/mobile-wallpapers-thumb/art/tree-boy.webp",
      "size": 6330128,
      "modified": "2025-10-26T15:19:42.227550+00:00",
      "category": "art"
    },
    {
      "filename": "window.png",
      "url": "wallpapers-mobile/art/window.png",
      "thumb_url": "thumbnail/mobile-wallpapers-thumb/art/window.webp",
      "size": 1807331,
      "modified": "2025-10-25T23:31:08.207886+00:00",
      "category": "art"
    },
    {
      "filename": "city.jpg",
      "url": "wallpapers-mobile/cyber-cityscape/city.jpg",
      "thumb_url": "thumbnail/mobile-wallpapers-thumb/cyber-cityscape/city.webp",
      "size": 137411,
      "modified": "2025-10-24T10:13:48.776155+00:00",
      "category": "cyber-cityscape"
    },
    {
      "filename": "house.jpg",
      "url": "wallpapers-mobile/cyber-cityscape/house.jpg",
      "thumb_url": "thumbnail/mobile-wallpapers-thumb/cyber-cityscape/house.webp",
      "size": 252642,
      "modified": "2025-10-24T10:13:48.778155+00:00",
      "category": "cyber-cityscape"
    },
    {
      "filename": "tower.jpg",
      "url": "wallpapers-mobile/cyber-cityscape/tower.jpg",
      "thumb_url": "thumbnail/mobile-wallpapers-thumb/cyber-cityscape/tower.webp",
      "size": 372724,
      "modified": "2025-10-25T21:03:57.538458+00:00",
      "category": "cyber-cityscape"
    },
    {
      "filename": "5825433.jpg",
      "url": "wallpapers-mobile/fun/5825433.jpg",
      "thumb_url": "thumbnail/mobile-wallpapers-thumb/fun/5825433.webp",
      "size": 839333,
      "modified": "2025-10-26T17:45:42.852696+00:00",
      "category": "fun"
    },
    {
      "filename": "dont-touch.jpg",
      "url": "wallpapers-mobile/fun/dont-touch.jpg",
      "thumb_url": "thumbnail/mobile-wallpapers-thumb/fun/dont-touch.webp",
      "size": 45784,
      "modified": "2025-10-26T15:27:57.687733+00:00",
      "category": "fun"
    },
    {
      "filename": "Gangsta_Pikachu.jpeg",
      "url": "wallpapers-mobile/fun/Gangsta_Pikachu.jpeg",
      "thumb_url": "thumbnail/mobile-wallpapers-thumb/fun/Gangsta_Pikachu.webp",
      "size": 125390,
      "modified": "2025-10-24T20:37:37.881479+00:00",
      "category": "fun"
    },
    {
      "filename": "locked.jpg",
      "url": "wallpapers-mobile/fun/locked.jpg",
      "thumb_url": "thumbnail/mobile-wallpapers-thumb/fun/locked.webp",
      "size": 40458,
      "modified": "2025-10-26T15:28:26.705916+00:00",
      "category": "fun"
    },
    {
      "filename": "botw-zelda.jpg",
      "url": "wallpapers-mobile/gaming/botw-zelda.jpg",
      "thumb_url": "thumbnail/mobile-wallpapers-thumb/gaming/botw-zelda.webp",
      "size": 83198,
      "modified": "2025-10-26T15:22:35.759677+00:00",
      "category": "gaming"
    },
    {
      "filename": "cyberpunk-2077-wallpaper.jpg",
      "url": "wallpapers-mobile/gaming/cyberpunk-2077-wallpaper.jpg",
      "thumb_url": "thumbnail/mobile-wallpapers-thumb/gaming/cyberpunk-2077-wallpaper.webp",
      "size": 888641,
      "modified": "2025-10-27T05:36:32.067629+00:00",
      "category": "gaming"
    },
    {
      "filename": "cyberpunk-2077.jpg",
      "url": "wallpapers-mobile/gaming/cyberpunk-2077.jpg",
      "thumb_url": "thumbnail/mobile-wallpapers-thumb/gaming/cyberpunk-2077.webp",
      "size": 758075,
      "modified": "2025-10-29T17:28:37.954732+00:00",
      "category": "gaming"
    },
    {
      "filename": "CYBERPUNK_samurai.jpeg",
      "url": "wallpapers-mobile/gaming/CYBERPUNK_samurai.jpeg",
      "thumb_url": "thumbnail/mobile-wallpapers-thumb/gaming/CYBERPUNK_samurai.webp",
      "size": 1469964,
      "modified": "2025-10-24T19:14:12.369885+00:00",
      "category": "gaming"
    },
    {
      "filename": "hollow-knight-wall.jpg",
      "url": "wallpapers-mobile/gaming/hollow-knight-wall.jpg",
      "thumb_url": "thumbnail/mobile-wallpapers-thumb/gaming/hollow-knight-wall.webp",
      "size": 97336,
      "modified": "2025-10-25T23:32:06.428534+00:00",
      "category": "gaming"
    },
    {
      "filename": "link-majoras-mask.jpg",
      "url": "wallpapers-mobile/gaming/link-majoras-mask.jpg",
      "thumb_url": "thumbnail/mobile-wallpapers-thumb/gaming/link-majoras-mask.webp",
      "size": 718575,
      "modified": "2025-10-26T15:22:15.593547+00:00",
      "category": "gaming"
    },
    {
      "filename": "link-zelda-forest-home.jpg",
      "url": "wallpapers-mobile/gaming/link-zelda-forest-home.jpg",
      "thumb_url": "thumbnail/mobile-wallpapers-thumb/gaming/link-zelda-forest-home.webp",
      "size": 898611,
      "modified": "2025-10-29T17:29:31.782044+00:00",
      "category": "gaming"
    },
    {
      "filename": "link-zelda-forest-lock.jpg",
      "url": "wallpapers-mobile/gaming/link-zelda-forest-lock.jpg",
      "thumb_url": "thumbnail/mobile-wallpapers-thumb/gaming/link-zelda-forest-lock.webp",
      "size": 869010,
      "modified": "2025-10-29T17:29:40.973869+00:00",
      "category": "gaming"
    },
    {
      "filename": "link.jpg",
      "url": "wallpapers-mobile/gaming/link.jpg",
      "thumb_url": "thumbnail/mobile-wallpapers-thumb/gaming/link.webp",
      "size": 526323,
      "modified": "2025-10-26T15:22:24.004601+00:00",
      "category": "gaming"
    },
    {
      "filename": "minecraft-epic-canyon.jpg",
      "url": "wallpapers-mobile/gaming/minecraft-epic-canyon.jpg",
      "thumb_url": "thumbnail/mobile-wallpapers-thumb/gaming/minecraft-epic-canyon.webp",
      "size": 1557688,
      "modified": "2025-10-29T17:29:14.767636+00:00",
      "category": "gaming"
    },
    {
      "filename": "minecraft-pixel.jpg",
      "url": "wallpapers-mobile/gaming/minecraft-pixel.jpg",
      "thumb_url": "thumbnail/mobile-wallpapers-thumb/gaming/minecraft-pixel.webp",
      "size": 539280,
      "modified": "2025-10-25T23:30:29.174972+00:00",
      "category": "gaming"
    },
    {
      "filename": "minecraft-sea.jpg",
      "url": "wallpapers-mobile/gaming/minecraft-sea.jpg",
      "thumb_url": "thumbnail/mobile-wallpapers-thumb/gaming/minecraft-sea.webp",
      "size": 350226,
      "modified": "2025-10-25T23:31:45.491078+00:00",
      "category": "gaming"
    },
    {
      "filename": "rdr-horse.jpg",
      "url": "wallpapers-mobile/gaming/rdr-horse.jpg",
      "thumb_url": "thumbnail/mobile-wallpapers-thumb/gaming/rdr-horse.webp",
      "size": 253596,
      "modified": "2025-10-26T15:23:25.665998+00:00",
      "category": "gaming"
    },
    {
      "filename": "Aesthetic_blue.jpeg",
      "url": "wallpapers-mobile/landscape/Aesthetic_blue.jpeg",
      "thumb_url": "thumbnail/mobile-wallpapers-thumb/landscape/Aesthetic_blue.webp",
      "size": 2341173,
      "modified": "2025-10-24T20:36:54.743869+00:00",
      "category": "landscape"
    },
    {
      "filename": "autumn-leaves.jpg",
      "url": "wallpapers-mobile/landscape/autumn-leaves.jpg",
      "thumb_url": "thumbnail/mobile-wallpapers-thumb/landscape/autumn-leaves.webp",
      "size": 1749097,
      "modified": "2025-10-29T17:30:43.375865+00:00",
      "category": "landscape"
    },
    {
      "filename": "blurry-brown-trees.jpg",
      "url": "wallpapers-mobile/landscape/blurry-brown-trees.jpg",
      "thumb_url": "thumbnail/mobile-wallpapers-thumb/landscape/blurry-brown-trees.webp",
      "size": 2747473,
      "modified": "2025-10-25T20:58:37.165065+00:00",
      "category": "landscape"
    },
    {
      "filename": "cat-in-forest.jpg",
      "url": "wallpapers-mobile/landscape/cat-in-forest.jpg",
      "thumb_url": "thumbnail/mobile-wallpapers-thumb/landscape/cat-in-forest.webp",
      "size": 554454,
      "modified": "2025-10-25T23:30:42.062582+00:00",
      "category": "landscape"
    },
    {
      "filename": "keyhole.png",
      "url": "wallpapers-mobile/landscape/keyhole.png",
      "thumb_url": "thumbnail/mobile-wallpapers-thumb/landscape/keyhole.webp",
      "size": 2053984,
      "modified": "2025-10-24T18:25:58.700937+00:00",
      "category": "landscape"
    },
    {
      "filename": "Landscape_moon.jpeg",
      "url": "wallpapers-mobile/landscape/Landscape_moon.jpeg",
      "thumb_url": "thumbnail/mobile-wallpapers-thumb/landscape/Landscape_moon.webp",
      "size": 351929,
      "modified": "2025-10-24T20:38:10.183229+00:00",
      "category": "landscape"
    },
    {
      "filename": "Magenta_Lightning.jpg",
      "url": "wallpapers-mobile/landscape/Magenta_Lightning.jpg",
      "thumb_url": "thumbnail/mobile-wallpapers-thumb/landscape/Magenta_Lightning.webp",
      "size": 481483,
      "modified": "2025-10-24T20:11:23.515805+00:00",
      "category": "landscape"
    },
    {
      "filename": "Minimal_landscape.jpeg",
      "url": "wallpapers-mobile/landscape/Minimal_landscape.jpeg",
      "thumb_url": "thumbnail/mobile-wallpapers-thumb/landscape/Minimal_landscape.webp",
      "size": 316729,
      "modified": "2025-10-25T20:59:54.614729+00:00",
      "category": "landscape"
    },
    {
      "filename": "Minimal_mountains_1.png",
      "url": "wallpapers-mobile/landscape/Minimal_mountains_1.png",
      "thumb_url": "thumbnail/mobile-wallpapers-thumb/landscape/Minimal_mountains_1.webp",
      "size": 136376,
      "modified": "2025-10-25T20:59:59.943048+00:00",
      "category": "landscape"
    },
    {
      "filename": "Minimal_mountains_2.jpeg",
      "url": "wallpapers-mobile/landscape/Minimal_mountains_2.jpeg",
      "thumb_url": "thumbnail/mobile-wallpapers-thumb/landscape/Minimal_mountains_2.webp",
      "size": 750770,
      "modified": "2025-10-25T21:00:02.397738+00:00",
      "category": "landscape"
    },
    {
      "filename": "Sky_fish.jpg",
      "url": "wallpapers-mobile/landscape/Sky_fish.jpg",
      "thumb_url": "thumbnail/mobile-wallpapers-thumb/landscape/Sky_fish.webp",
      "size": 256948,
      "modified": "2025-10-24T10:13:49.186161+00:00",
      "category": "landscape"
    },
    {
      "filename": "dont-doubt.jpg",
      "url": "wallpapers-mobile/motivational/dont-doubt.jpg",
      "thumb_url": "thumbnail/mobile-wallpapers-thumb/motivational/dont-doubt.webp",
      "size": 35518,
      "modified": "2025-10-26T20:21:25.415871+00:00",
      "category": "motivational"
    },
    {
      "filename": "keep-going.jpg",
      "url": "wallpapers-mobile/motivational/keep-going.jpg",
      "thumb_url": "thumbnail/mobile-wallpapers-thumb/motivational/keep-going.webp",
      "size": 59758,
      "modified": "2025-10-26T15:26:15.763086+00:00",
      "category": "motivational"
    },
    {
      "filename": "motivational-background-photo.jpg",
      "url": "wallpapers-mobile/motivational/motivational-background-photo.jpg",
      "thumb_url": "thumbnail/mobile-wallpapers-thumb/motivational/motivational-background-photo.webp",
      "size": 189747,
      "modified": "2025-10-26T20:21:55.188603+00:00",
      "category": "motivational"
    },
    {
      "filename": "motivational-wallpaper.jpg",
      "url": "wallpapers-mobile/motivational/motivational-wallpaper.jpg",
      "thumb_url": "thumbnail/mobile-wallpapers-thumb/motivational/motivational-wallpaper.webp",
      "size": 187681,
      "modified": "2025-10-26T15:27:28.060545+00:00",
      "category": "motivational"
    },
    {
      "filename": "ash.jpg",
      "url": "wallpapers-mobile/pokemon/ash.jpg",
      "thumb_url": "thumbnail/mobile-wallpapers-thumb/pokemon/ash.webp",
      "size": 855476,
      "modified": "2025-10-26T15:30:17.818618+00:00",
      "category": "pokemon"
    },
    {
      "filename": "gyarados.jpg",
      "url": "wallpapers-mobile/pokemon/gyarados.jpg",
      "thumb_url": "thumbnail/mobile-wallpapers-thumb/pokemon/gyarados.webp",
      "size": 171445,
      "modified": "2025-10-28T17:37:10.509806+00:00",
      "category": "pokemon"
    },
    {
      "filename": "hoen-trio.jpg",
      "url": "wallpapers-mobile/pokemon/hoen-trio.jpg",
      "thumb_url": "thumbnail/mobile-wallpapers-thumb/pokemon/hoen-trio.webp",
      "size": 696850,
      "modified": "2025-10-29T13:30:00.656947+00:00",
      "category": "pokemon"
    },
    {
      "filename": "pokemon-blue.jpg",
      "url": "wallpapers-mobile/pokemon/pokemon-blue.jpg",
      "thumb_url": "thumbnail/mobile-wallpapers-thumb/pokemon/pokemon-blue.webp",
      "size": 464983,
      "modified": "2025-10-28T17:36:40.464432+00:00",
      "category": "pokemon"
    },
    {
      "filename": "pokemon-lugia.jpg",
      "url": "wallpapers-mobile/pokemon/pokemon-lugia.jpg",
      "thumb_url": "thumbnail/mobile-wallpapers-thumb/pokemon/pokemon-lugia.webp",
      "size": 348640,
      "modified": "2025-10-25T23:32:17.459128+00:00",
      "category": "pokemon"
    },
    {
      "filename": "pokemon.jpg",
      "url": "wallpapers-mobile/pokemon/pokemon.jpg",
      "thumb_url": "thumbnail/mobile-wallpapers-thumb/pokemon/pokemon.webp",
      "size": 68023,
      "modified": "2025-10-28T17:37:02.395705+00:00",
      "category": "pokemon"
    },
    {
      "filename": "totodile.jpg",
      "url": "wallpapers-mobile/pokemon/totodile.jpg",
      "thumb_url": "thumbnail/mobile-wallpapers-thumb/pokemon/totodile.webp",
      "size": 1557371,
      "modified": "2025-10-29T17:30:03.769074+00:00",
      "category": "pokemon"
    },
    {
      "filename": "Astronaut.jpeg",
      "url": "wallpapers-mobile/sci-fi/Astronaut.jpeg",
      "thumb_url": "thumbnail/mobile-wallpapers-thumb/sci-fi/Astronaut.webp",
      "size": 187026,
      "modified": "2025-10-24T20:09:01.111716+00:00",
      "category": "sci-fi"
    },
    {
      "filename": "astronaut_space.jpg",
      "url": "wallpapers-mobile/sci-fi/astronaut_space.jpg",
      "thumb_url": "thumbnail/mobile-wallpapers-thumb/sci-fi/astronaut_space.webp",
      "size": 682862,
      "modified": "2025-10-24T20:09:16.227277+00:00",
      "category": "sci-fi"
    },
    {
      "filename": "city_boat.jpg",
      "url": "wallpapers-mobile/sci-fi/city_boat.jpg",
      "thumb_url": "thumbnail/mobile-wallpapers-thumb/sci-fi/city_boat.webp",
      "size": 657302,
      "modified": "2025-10-25T21:01:04.059237+00:00",
      "category": "sci-fi"
    },
    {
      "filename": "finding_life.png",
      "url": "wallpapers-mobile/sci-fi/finding_life.png",
      "thumb_url": "thumbnail/mobile-wallpapers-thumb/sci-fi/finding_life.webp",
      "size": 4847155,
      "modified": "2025-10-24T20:05:33.379583+00:00",
      "category": "sci-fi"
    },
    {
      "filename": "husk.jpg",
      "url": "wallpapers-mobile/sci-fi/husk.jpg",
      "thumb_url": "thumbnail/mobile-wallpapers-thumb/sci-fi/husk.webp",
      "size": 1536597,
      "modified": "2025-10-24T20:42:12.145242+00:00",
      "category": "sci-fi"
    },
    {
      "filename": "Saturn.jpeg",
      "url": "wallpapers-mobile/sci-fi/Saturn.jpeg",
      "thumb_url": "thumbnail/mobile-wallpapers-thumb/sci-fi/Saturn.webp",
      "size": 623399,
      "modified": "2025-10-25T21:01:36.827484+00:00",
      "category": "sci-fi"
    },
    {
      "filename": "ERR_NAME.jpeg",
      "url": "wallpapers-mobile/tech/ERR_NAME.jpeg",
      "thumb_url": "thumbnail/mobile-wallpapers-thumb/tech/ERR_NAME.webp",
      "size": 403441,
      "modified": "2025-10-24T19:15:01.894908+00:00",
      "category": "tech"
    },
    {
      "filename": "laptop.jpg",
      "url": "wallpapers-mobile/tech/laptop.jpg",
      "thumb_url": "thumbnail/mobile-wallpapers-thumb/tech/laptop.webp",
      "size": 1021283,
      "modified": "2025-10-26T17:44:04.809696+00:00",
      "category": "tech"
    },
    {
      "filename": "mobile-lego.jpg",
      "url": "wallpapers-mobile/tech/mobile-lego.jpg",
      "thumb_url": "thumbnail/mobile-wallpapers-thumb/tech/mobile-lego.webp",
      "size": 1297668,
      "modified": "2025-10-26T17:43:46.998208+00:00",
      "category": "tech"
    },
    {
      "filename": "no-internet-2.jpg",
      "url": "wallpapers-mobile/tech/no-internet-2.jpg",
      "thumb_url": "thumbnail/mobile-wallpapers-thumb/tech/no-internet-2.webp",
      "size": 276358,
      "modified": "2025-10-25T23:31:29.716336+00:00",
      "category": "tech"
    },
    {
      "filename": "no-internet.jpg",
      "url": "wallpapers-mobile/tech/no-internet.jpg",
      "thumb_url": "thumbnail/mobile-wallpapers-thumb/tech/no-internet.webp",
      "size": 178423,
      "modified": "2025-10-25T23:31:19.394652+00:00",
      "category": "tech"
    }
  ]
}